convertex/main.py
convertex-0.1.3.dist-info/LICENSE
convertex-0.1.3.dist-info/METADATA
convertex-0.1.3.dist-info/WHEEL
convertex-0.1.3.dist-info/entry_points.txt
convertex-0.1.3.dist-info/RECORD
